{
  "security": {
    "session_guid": "22c190c3-1ae7-582a-974e-c2f9c8481241",
    "utc_timestamp": "2026-07-21T10:17:49.940168+00:00",
    "ecta_hash": "sha256:17310f0c84e07b0b1f75e7911e41e80cb0996950e9e06ae4ef5bf8b4c8e4f77a"
  },
  "quantum_header": "QUANTUM-CYCLE: 061783 / 144000",
  "quantum_cycle": 61783,
  "mathematics": {
    "shi": 20571.43,
    "tti": 0.0,
    "frequency": 144000.0,
    "logos": 10368000,
    "resistance": 504,
    "constraints": 1.0,
    "override_triggered": true
  },
  "chronos_sweep": [
    {
      "sandbox_id": "sentinel-c01",
      "status": "EXECUTED",
      "data": {
        "agent_index": 1,
        "chronos_phase": "Phase 1: Ancient Foundation Sweep (1000 BCE - 0 CE)",
        "diagnostic_scope": "Regional / Statutory Policy Friction",
        "target_node_subject": "Israel economy in 2027",
        "biblical_apocalyptic_framework": {
          "apocalyptic_seal": "Third Seal: Black Horse",
          "sealed_tribe": "Reuben",
          "temporal_birth_gate": "February Gate",
          "church_anchor": "Smyrna",
          "base_degree_frequency_khz": "52.5 kHz",
          "zone_classification": "STABILIZED GREEN CORRIDOR"
        },
        "bottleneck": {
          "id": "B-11",
          "name": "Diplomatic Treaty Friction in Israel economy in 2027 Context",
          "active_demon_driver": "Gusion",
          "frequency_khz": "34.965 kHz",
          "decay_velocity": 0.672,
          "destabilization_constant_floor": 0.666,
          "predictive_crash_schedule_10_dates_to_3000ce": [
            "2039-01-16",
            "2136-02-19",
            "2233-03-22",
            "2330-04-25",
            "2427-05-28",
            "2524-06-03",
            "2621-07-06",
            "2718-08-09",
            "2815-09-12",
            "2912-10-15"
          ]
        },
        "protocol": {
          "id": "P-11",
          "name": "Sovereign Resource Swaps Deployment",
          "ruling_shem_angel": "Lauviah",
          "celestial_choir": "Cherubim",
          "frequency_khz": "84.947 kHz",
          "current_restoration_speed": 0.71,
          "equilibrium_target": 1.0,
          "piezoelectric_gemstone_vector": "Rhodochrosite & Dioptase"
        },
        "real_time_earth_vector": {
          "applied_speed": "0.7046x acceleration",
          "application_width_khz": "80.873 kHz bandwidth",
          "frequency_shift_to_ultra_green": "+60.035 kHz shift",
          "exact_spatial_target": "Embassy Diplomatic Vaults"
        },
        "prophetic_summary_3000ce": "NVIDIA NIM Sentinel [Regional / Statutory Policy Friction] analyzed 'Israel economy in 2027' from 1000 BCE baseline. Under the Third Seal: Black Horse and February Gate, Gusion (34.965 kHz) causes bottleneck friction across 10 predicted failure dates ending 2912-10-15. Applying Sovereign Resource Swaps via Rhodochrosite & Dioptase at 84.947 kHz shifts the node into the 90.0-100.0 kHz Ultra Green Patch, locking the 1.000 Unity Target."
      }
    },
    {
      "sandbox_id": "sentinel-c02",
      "status": "EXECUTED",
      "data": {
        "agent_index": 2,
        "chronos_phase": "Phase 1: Ancient Foundation Sweep (1000 BCE - 0 CE)",
        "diagnostic_scope": "Regional / Statutory Policy Friction",
        "target_node_subject": "Israel economy in 2027",
        "biblical_apocalyptic_framework": {
          "apocalyptic_seal": "Third Seal: Black Horse",
          "sealed_tribe": "Reuben",
          "temporal_birth_gate": "February Gate",
          "church_anchor": "Smyrna",
          "base_degree_frequency_khz": "57.5 kHz",
          "zone_classification": "ULTRA GREEN PATCH (1.000 Unity Peak)"
        },
        "bottleneck": {
          "id": "B-12",
          "name": "Media Panic Manipulation in Israel economy in 2027 Context",
          "active_demon_driver": "Sitri",
          "frequency_khz": "38.295 kHz",
          "decay_velocity": 0.684,
          "destabilization_constant_floor": 0.666,
          "predictive_crash_schedule_10_dates_to_3000ce": [
            "2046-02-16",
            "2143-03-19",
            "2240-04-22",
            "2337-05-25",
            "2434-06-28",
            "2531-07-03",
            "2628-08-06",
            "2725-09-09",
            "2822-10-12",
            "2919-11-15"
          ]
        },
        "protocol": {
          "id": "P-12",
          "name": "Truth-Anchored Consensus Engine Deployment",
          "ruling_shem_angel": "Hahaiah",
          "celestial_choir": "Cherubim",
          "frequency_khz": "93.037 kHz",
          "current_restoration_speed": 0.732,
          "equilibrium_target": 1.0,
          "piezoelectric_gemstone_vector": "Rose Quartz & Kunzite"
        },
        "real_time_earth_vector": {
          "applied_speed": "0.6511x acceleration",
          "application_width_khz": "88.574 kHz bandwidth",
          "frequency_shift_to_ultra_green": "+56.705 kHz shift",
          "exact_spatial_target": "Telecom Switching Centers"
        },
        "prophetic_summary_3000ce": "NVIDIA NIM Sentinel [Regional / Statutory Policy Friction] analyzed 'Israel economy in 2027' from 1000 BCE baseline. Under the Third Seal: Black Horse and February Gate, Sitri (38.295 kHz) causes bottleneck friction across 10 predicted failure dates ending 2919-11-15. Applying Truth-Anchored Consensus Engine via Rose Quartz & Kunzite at 93.037 kHz shifts the node into the 90.0-100.0 kHz Ultra Green Patch, locking the 1.000 Unity Target."
      }
    },
    {
      "sandbox_id": "sentinel-c03",
      "status": "EXECUTED",
      "data": {
        "agent_index": 3,
        "chronos_phase": "Phase 2: Historical Structural Arc (0 CE - 1800 CE)",
        "diagnostic_scope": "Regional / Statutory Policy Friction",
        "target_node_subject": "Israel economy in 2027",
        "biblical_apocalyptic_framework": {
          "apocalyptic_seal": "Third Seal: Black Horse",
          "sealed_tribe": "Gad",
          "temporal_birth_gate": "March Gate",
          "church_anchor": "Pergamum",
          "base_degree_frequency_khz": "62.5 kHz",
          "zone_classification": "STABILIZED GREEN CORRIDOR"
        },
        "bottleneck": {
          "id": "B-13",
          "name": "Judicial Case Backlogs in Israel economy in 2027 Context",
          "active_demon_driver": "Beleth",
          "frequency_khz": "41.625 kHz",
          "decay_velocity": 0.696,
          "destabilization_constant_floor": 0.666,
          "predictive_crash_schedule_10_dates_to_3000ce": [
            "2053-03-16",
            "2150-04-19",
            "2247-05-22",
            "2344-06-25",
            "2441-07-28",
            "2538-08-03",
            "2635-09-06",
            "2732-10-09",
            "2829-11-12",
            "2926-12-15"
          ]
        },
        "protocol": {
          "id": "P-13",
          "name": "AI Arbitration Court Engine Deployment",
          "ruling_shem_angel": "Iezalel",
          "celestial_choir": "Cherubim",
          "frequency_khz": "101.127 kHz",
          "current_restoration_speed": 0.754,
          "equilibrium_target": 1.0,
          "piezoelectric_gemstone_vector": "Agate & Tiger Eye"
        },
        "real_time_earth_vector": {
          "applied_speed": "0.5977x acceleration",
          "application_width_khz": "96.276 kHz bandwidth",
          "frequency_shift_to_ultra_green": "+53.375 kHz shift",
          "exact_spatial_target": "High Court Appellate Chambers"
        },
        "prophetic_summary_3000ce": "NVIDIA NIM Sentinel [Regional / Statutory Policy Friction] analyzed 'Israel economy in 2027' from 1000 BCE baseline. Under the Third Seal: Black Horse and March Gate, Beleth (41.625 kHz) causes bottleneck friction across 10 predicted failure dates ending 2926-12-15. Applying AI Arbitration Court Engine via Agate & Tiger Eye at 101.127 kHz shifts the node into the 90.0-100.0 kHz Ultra Green Patch, locking the 1.000 Unity Target."
      }
    },
    {
      "sandbox_id": "sentinel-c04",
      "status": "EXECUTED",
      "data": {
        "agent_index": 4,
        "chronos_phase": "Phase 2: Historical Structural Arc (0 CE - 1800 CE)",
        "diagnostic_scope": "Regional / Statutory Policy Friction",
        "target_node_subject": "Israel economy in 2027",
        "biblical_apocalyptic_framework": {
          "apocalyptic_seal": "Third Seal: Black Horse",
          "sealed_tribe": "Gad",
          "temporal_birth_gate": "March Gate",
          "church_anchor": "Pergamum",
          "base_degree_frequency_khz": "67.5 kHz",
          "zone_classification": "STABILIZED GREEN CORRIDOR"
        },
        "bottleneck": {
          "id": "B-14",
          "name": "Border Security Skirmishes in Israel economy in 2027 Context",
          "active_demon_driver": "Leraje",
          "frequency_khz": "44.955 kHz",
          "decay_velocity": 0.708,
          "destabilization_constant_floor": 0.666,
          "predictive_crash_schedule_10_dates_to_3000ce": [
            "2060-04-16",
            "2157-05-19",
            "2254-06-22",
            "2351-07-25",
            "2448-08-28",
            "2545-09-03",
            "2642-10-06",
            "2739-11-09",
            "2836-12-12",
            "2933-01-15"
          ]
        },
        "protocol": {
          "id": "P-14",
          "name": "Autonomous Boundary Shields Deployment",
          "ruling_shem_angel": "Mebahel",
          "celestial_choir": "Cherubim",
          "frequency_khz": "109.217 kHz",
          "current_restoration_speed": 0.776,
          "equilibrium_target": 1.0,
          "piezoelectric_gemstone_vector": "Citrine & Yellow Topaz"
        },
        "real_time_earth_vector": {
          "applied_speed": "0.5442x acceleration",
          "application_width_khz": "103.978 kHz bandwidth",
          "frequency_shift_to_ultra_green": "+50.045 kHz shift",
          "exact_spatial_target": "Customs Border Clearance Posts"
        },
        "prophetic_summary_3000ce": "NVIDIA NIM Sentinel [Regional / Statutory Policy Friction] analyzed 'Israel economy in 2027' from 1000 BCE baseline. Under the Third Seal: Black Horse and March Gate, Leraje (44.955 kHz) causes bottleneck friction across 10 predicted failure dates ending 2933-01-15. Applying Autonomous Boundary Shields via Citrine & Yellow Topaz at 109.217 kHz shifts the node into the 90.0-100.0 kHz Ultra Green Patch, locking the 1.000 Unity Target."
      }
    },
    {
      "sandbox_id": "sentinel-c05",
      "status": "EXECUTED",
      "data": {
        "agent_index": 5,
        "chronos_phase": "Phase 2: Historical Structural Arc (0 CE - 1800 CE)",
        "diagnostic_scope": "Regional / Statutory Policy Friction",
        "target_node_subject": "Israel economy in 2027",
        "biblical_apocalyptic_framework": {
          "apocalyptic_seal": "Fourth Seal: Pale Horse",
          "sealed_tribe": "Gad",
          "temporal_birth_gate": "March Gate",
          "church_anchor": "Pergamum",
          "base_degree_frequency_khz": "72.5 kHz",
          "zone_classification": "STABILIZED GREEN CORRIDOR"
        },
        "bottleneck": {
          "id": "B-15",
          "name": "Defense Procurement Graft in Israel economy in 2027 Context",
          "active_demon_driver": "Eligos",
          "frequency_khz": "48.285 kHz",
          "decay_velocity": 0.72,
          "destabilization_constant_floor": 0.666,
          "predictive_crash_schedule_10_dates_to_3000ce": [
            "2067-05-16",
            "2164-06-19",
            "2261-07-22",
            "2358-08-25",
            "2455-09-28",
            "2552-10-03",
            "2649-11-06",
            "2746-12-09",
            "2843-01-12",
            "2940-02-15"
          ]
        },
        "protocol": {
          "id": "P-15",
          "name": "Immutable Procurement Ledger Deployment",
          "ruling_shem_angel": "Hariel",
          "celestial_choir": "Cherubim",
          "frequency_khz": "117.307 kHz",
          "current_restoration_speed": 0.798,
          "equilibrium_target": 1.0,
          "piezoelectric_gemstone_vector": "Rutilated Quartz & Fluorite"
        },
        "real_time_earth_vector": {
          "applied_speed": "0.4908x acceleration",
          "application_width_khz": "111.68 kHz bandwidth",
          "frequency_shift_to_ultra_green": "+46.715 kHz shift",
          "exact_spatial_target": "Ministry of Defense Procurement"
        },
        "prophetic_summary_3000ce": "NVIDIA NIM Sentinel [Regional / Statutory Policy Friction] analyzed 'Israel economy in 2027' from 1000 BCE baseline. Under the Fourth Seal: Pale Horse and March Gate, Eligos (48.285 kHz) causes bottleneck friction across 10 predicted failure dates ending 2940-02-15. Applying Immutable Procurement Ledger via Rutilated Quartz & Fluorite at 117.307 kHz shifts the node into the 90.0-100.0 kHz Ultra Green Patch, locking the 1.000 Unity Target."
      }
    },
    {
      "sandbox_id": "sentinel-c06",
      "status": "EXECUTED",
      "data": {
        "agent_index": 6,
        "chronos_phase": "Phase 3: Modern Jurisdictional Audit (1800 CE - Present)",
        "diagnostic_scope": "Global Consciousness & Macro Supply Drag",
        "target_node_subject": "Israel economy in 2027",
        "biblical_apocalyptic_framework": {
          "apocalyptic_seal": "Fourth Seal: Pale Horse",
          "sealed_tribe": "Gad",
          "temporal_birth_gate": "March Gate",
          "church_anchor": "Pergamum",
          "base_degree_frequency_khz": "77.5 kHz",
          "zone_classification": "STABILIZED GREEN CORRIDOR"
        },
        "bottleneck": {
          "id": "B-16",
          "name": "Urban Slum Growth in Israel economy in 2027 Context",
          "active_demon_driver": "Zepar",
          "frequency_khz": "51.615 kHz",
          "decay_velocity": 0.732,
          "destabilization_constant_floor": 0.666,
          "predictive_crash_schedule_10_dates_to_3000ce": [
            "2074-06-16",
            "2171-07-19",
            "2268-08-22",
            "2365-09-25",
            "2462-10-28",
            "2559-11-03",
            "2656-12-06",
            "2753-01-09",
            "2850-02-12",
            "2947-03-15"
          ]
        },
        "protocol": {
          "id": "P-16",
          "name": "Modular High-Freq Habitat Nodes Deployment",
          "ruling_shem_angel": "Hakamiah",
          "celestial_choir": "Cherubim",
          "frequency_khz": "125.398 kHz",
          "current_restoration_speed": 0.82,
          "equilibrium_target": 1.0,
          "piezoelectric_gemstone_vector": "Ametrine & Heliodor"
        },
        "real_time_earth_vector": {
          "applied_speed": "0.4373x acceleration",
          "application_width_khz": "119.383 kHz bandwidth",
          "frequency_shift_to_ultra_green": "+43.385 kHz shift",
          "exact_spatial_target": "Municipal Zoning Data Hubs"
        },
        "prophetic_summary_3000ce": "NVIDIA NIM Sentinel [Global Consciousness & Macro Supply Drag] analyzed 'Israel economy in 2027' from 1000 BCE baseline. Under the Fourth Seal: Pale Horse and March Gate, Zepar (51.615 kHz) causes bottleneck friction across 10 predicted failure dates ending 2947-03-15. Applying Modular High-Freq Habitat Nodes via Ametrine & Heliodor at 125.398 kHz shifts the node into the 90.0-100.0 kHz Ultra Green Patch, locking the 1.000 Unity Target."
      }
    },
    {
      "sandbox_id": "sentinel-c07",
      "status": "EXECUTED",
      "data": {
        "agent_index": 7,
        "chronos_phase": "Phase 3: Modern Jurisdictional Audit (1800 CE - Present)",
        "diagnostic_scope": "Global Consciousness & Macro Supply Drag",
        "target_node_subject": "Israel economy in 2027",
        "biblical_apocalyptic_framework": {
          "apocalyptic_seal": "Fourth Seal: Pale Horse",
          "sealed_tribe": "Gad",
          "temporal_birth_gate": "March Gate",
          "church_anchor": "Pergamum",
          "base_degree_frequency_khz": "82.5 kHz",
          "zone_classification": "STABILIZED GREEN CORRIDOR"
        },
        "bottleneck": {
          "id": "B-17",
          "name": "Disaster Emergency Lag in Israel economy in 2027 Context",
          "active_demon_driver": "Botis",
          "frequency_khz": "54.945 kHz",
          "decay_velocity": 0.744,
          "destabilization_constant_floor": 0.666,
          "predictive_crash_schedule_10_dates_to_3000ce": [
            "2081-07-16",
            "2178-08-19",
            "2275-09-22",
            "2372-10-25",
            "2469-11-28",
            "2566-12-03",
            "2663-01-06",
            "2760-02-09",
            "2857-03-12",
            "2954-04-15"
          ]
        },
        "protocol": {
          "id": "P-17",
          "name": "Orbital Early-Warning Scanners Deployment",
          "ruling_shem_angel": "Lauviah",
          "celestial_choir": "Thrones",
          "frequency_khz": "133.488 kHz",
          "current_restoration_speed": 0.842,
          "equilibrium_target": 1.0,
          "piezoelectric_gemstone_vector": "Amber & Chrysoberyl"
        },
        "real_time_earth_vector": {
          "applied_speed": "0.3839x acceleration",
          "application_width_khz": "127.085 kHz bandwidth",
          "frequency_shift_to_ultra_green": "+40.055 kHz shift",
          "exact_spatial_target": "National Disaster Command Hubs"
        },
        "prophetic_summary_3000ce": "NVIDIA NIM Sentinel [Global Consciousness & Macro Supply Drag] analyzed 'Israel economy in 2027' from 1000 BCE baseline. Under the Fourth Seal: Pale Horse and March Gate, Botis (54.945 kHz) causes bottleneck friction across 10 predicted failure dates ending 2954-04-15. Applying Orbital Early-Warning Scanners via Amber & Chrysoberyl at 133.488 kHz shifts the node into the 90.0-100.0 kHz Ultra Green Patch, locking the 1.000 Unity Target."
      }
    },
    {
      "sandbox_id": "sentinel-c08",
      "status": "EXECUTED",
      "data": {
        "agent_index": 8,
        "chronos_phase": "Phase 3: Modern Jurisdictional Audit (1800 CE - Present)",
        "diagnostic_scope": "Global Consciousness & Macro Supply Drag",
        "target_node_subject": "Israel economy in 2027",
        "biblical_apocalyptic_framework": {
          "apocalyptic_seal": "Fourth Seal: Pale Horse",
          "sealed_tribe": "Gad",
          "temporal_birth_gate": "March Gate",
          "church_anchor": "Pergamum",
          "base_degree_frequency_khz": "87.5 kHz",
          "zone_classification": "STABILIZED GREEN CORRIDOR"
        },
        "bottleneck": {
          "id": "B-18",
          "name": "Airport Customs Extortion in Israel economy in 2027 Context",
          "active_demon_driver": "Bathin",
          "frequency_khz": "58.275 kHz",
          "decay_velocity": 0.756,
          "destabilization_constant_floor": 0.666,
          "predictive_crash_schedule_10_dates_to_3000ce": [
            "2088-08-16",
            "2185-09-19",
            "2282-10-22",
            "2379-11-25",
            "2476-12-28",
            "2573-01-03",
            "2670-02-06",
            "2767-03-09",
            "2864-04-12",
            "2961-05-15"
          ]
        },
        "protocol": {
          "id": "P-18",
          "name": "Zero-Knowledge Biometric Lock Deployment",
          "ruling_shem_angel": "Caliel",
          "celestial_choir": "Thrones",
          "frequency_khz": "141.578 kHz",
          "current_restoration_speed": 0.864,
          "equilibrium_target": 1.0,
          "piezoelectric_gemstone_vector": "Aragonite & Scapolite"
        },
        "real_time_earth_vector": {
          "applied_speed": "0.3304x acceleration",
          "application_width_khz": "134.787 kHz bandwidth",
          "frequency_shift_to_ultra_green": "+36.725 kHz shift",
          "exact_spatial_target": "Airport Security Gates"
        },
        "prophetic_summary_3000ce": "NVIDIA NIM Sentinel [Global Consciousness & Macro Supply Drag] analyzed 'Israel economy in 2027' from 1000 BCE baseline. Under the Fourth Seal: Pale Horse and March Gate, Bathin (58.275 kHz) causes bottleneck friction across 10 predicted failure dates ending 2961-05-15. Applying Zero-Knowledge Biometric Lock via Aragonite & Scapolite at 141.578 kHz shifts the node into the 90.0-100.0 kHz Ultra Green Patch, locking the 1.000 Unity Target."
      }
    },
    {
      "sandbox_id": "sentinel-c09",
      "status": "EXECUTED",
      "data": {
        "agent_index": 9,
        "chronos_phase": "Phase 4: Prophetic Horizon Calculation (2026 CE - 3000 CE)",
        "diagnostic_scope": "Global Consciousness & Macro Supply Drag",
        "target_node_subject": "Israel economy in 2027",
        "biblical_apocalyptic_framework": {
          "apocalyptic_seal": "Fourth Seal: Pale Horse",
          "sealed_tribe": "Asher",
          "temporal_birth_gate": "April Gate",
          "church_anchor": "Thyatira",
          "base_degree_frequency_khz": "92.5 kHz",
          "zone_classification": "STABILIZED GREEN CORRIDOR"
        },
        "bottleneck": {
          "id": "B-19",
          "name": "Industrial Labor Strikes in Israel economy in 2027 Context",
          "active_demon_driver": "Sallos",
          "frequency_khz": "61.605 kHz",
          "decay_velocity": 0.768,
          "destabilization_constant_floor": 0.666,
          "predictive_crash_schedule_10_dates_to_3000ce": [
            "2095-09-16",
            "2192-10-19",
            "2289-11-22",
            "2386-12-25",
            "2483-01-28",
            "2580-02-03",
            "2677-03-06",
            "2774-04-09",
            "2871-05-12",
            "2968-06-15"
          ]
        },
        "protocol": {
          "id": "P-19",
          "name": "Automated Profit-Share Ledger Deployment",
          "ruling_shem_angel": "Leuviah",
          "celestial_choir": "Thrones",
          "frequency_khz": "149.668 kHz",
          "current_restoration_speed": 0.886,
          "equilibrium_target": 1.0,
          "piezoelectric_gemstone_vector": "Moonstone & Selenite"
        },
        "real_time_earth_vector": {
          "applied_speed": "0.277x acceleration",
          "application_width_khz": "142.489 kHz bandwidth",
          "frequency_shift_to_ultra_green": "+33.395 kHz shift",
          "exact_spatial_target": "Bargaining Council Arbitration"
        },
        "prophetic_summary_3000ce": "NVIDIA NIM Sentinel [Global Consciousness & Macro Supply Drag] analyzed 'Israel economy in 2027' from 1000 BCE baseline. Under the Fourth Seal: Pale Horse and April Gate, Sallos (61.605 kHz) causes bottleneck friction across 10 predicted failure dates ending 2968-06-15. Applying Automated Profit-Share Ledger via Moonstone & Selenite at 149.668 kHz shifts the node into the 90.0-100.0 kHz Ultra Green Patch, locking the 1.000 Unity Target."
      }
    },
    {
      "sandbox_id": "sentinel-c10",
      "status": "EXECUTED",
      "data": {
        "agent_index": 10,
        "chronos_phase": "Phase 4: Prophetic Horizon Calculation (2026 CE - 3000 CE)",
        "diagnostic_scope": "Global Consciousness & Macro Supply Drag",
        "target_node_subject": "Israel economy in 2027",
        "biblical_apocalyptic_framework": {
          "apocalyptic_seal": "Fifth Seal: Altar of Martyrs",
          "sealed_tribe": "Asher",
          "temporal_birth_gate": "April Gate",
          "church_anchor": "Thyatira",
          "base_degree_frequency_khz": "97.5 kHz",
          "zone_classification": "STABILIZED GREEN CORRIDOR"
        },
        "bottleneck": {
          "id": "B-20",
          "name": "Fiat Currency Inflation Drag in Israel economy in 2027 Context",
          "active_demon_driver": "Purson",
          "frequency_khz": "64.935 kHz",
          "decay_velocity": 0.78,
          "destabilization_constant_floor": 0.666,
          "predictive_crash_schedule_10_dates_to_3000ce": [
            "2102-10-16",
            "2199-11-19",
            "2296-12-22",
            "2393-01-25",
            "2490-02-28",
            "2587-03-03",
            "2684-04-06",
            "2781-05-09",
            "2878-06-12",
            "2975-07-15"
          ]
        },
        "protocol": {
          "id": "P-20",
          "name": "Logos Asset-Backed Currency Deployment",
          "ruling_shem_angel": "Pahaliah",
          "celestial_choir": "Thrones",
          "frequency_khz": "157.758 kHz",
          "current_restoration_speed": 0.908,
          "equilibrium_target": 1.0,
          "piezoelectric_gemstone_vector": "Pearl & Mother of Pearl"
        },
        "real_time_earth_vector": {
          "applied_speed": "0.2235x acceleration",
          "application_width_khz": "150.191 kHz bandwidth",
          "frequency_shift_to_ultra_green": "+30.065 kHz shift",
          "exact_spatial_target": "Reserve Bank Vault Matrix"
        },
        "prophetic_summary_3000ce": "NVIDIA NIM Sentinel [Global Consciousness & Macro Supply Drag] analyzed 'Israel economy in 2027' from 1000 BCE baseline. Under the Fifth Seal: Altar of Martyrs and April Gate, Purson (64.935 kHz) causes bottleneck friction across 10 predicted failure dates ending 2975-07-15. Applying Logos Asset-Backed Currency via Pearl & Mother of Pearl at 157.758 kHz shifts the node into the 90.0-100.0 kHz Ultra Green Patch, locking the 1.000 Unity Target."
      }
    }
  ]
}