{
  "quantum_header": "QUANTUM-CYCLE: 059763 / 144000",
  "quantum_cycle": 59763,
  "chronos_sweep": [
    {
      "sandbox_id": "sentinel-c01",
      "status": "EXECUTED",
      "data": {
        "agent_index": 1,
        "chronos_phase": "Phase 1: Ancient Foundation Sweep (1000 BCE - 0 CE)",
        "diagnostic_scope": "Regional / Statutory Policy Friction",
        "target_node_subject": "South Africa",
        "biblical_apocalyptic_framework": {
          "apocalyptic_seal": "Fourth Seal: Pale Horse",
          "sealed_tribe": "Gad",
          "temporal_birth_gate": "March Gate",
          "church_anchor": "Pergamum",
          "base_degree_frequency_khz": "82.5 kHz",
          "zone_classification": "STABILIZED GREEN CORRIDOR"
        },
        "bottleneck": {
          "id": "B-17",
          "name": "Disaster Emergency Lag in South Africa Context",
          "active_demon_driver": "Botis",
          "frequency_khz": "54.945 kHz",
          "decay_velocity": 0.672,
          "destabilization_constant_floor": 0.666,
          "predictive_crash_schedule_10_dates_to_3000ce": [
            "2029-01-12",
            "2126-02-15",
            "2223-03-18",
            "2320-04-21",
            "2417-05-24",
            "2514-06-27",
            "2611-07-02",
            "2708-08-05",
            "2805-09-08",
            "2902-10-11"
          ]
        },
        "protocol": {
          "id": "P-17",
          "name": "Orbital Early-Warning Scanners Deployment",
          "ruling_shem_angel": "Lauviah",
          "celestial_choir": "Thrones",
          "frequency_khz": "133.488 kHz",
          "current_restoration_speed": 0.71,
          "equilibrium_target": 1.0,
          "piezoelectric_gemstone_vector": "Amber & Chrysoberyl"
        },
        "real_time_earth_vector": {
          "applied_speed": "0.7046x acceleration",
          "application_width_khz": "127.085 kHz bandwidth",
          "frequency_shift_to_ultra_green": "+40.055 kHz shift",
          "exact_spatial_target": "National Disaster Command Hubs"
        },
        "prophetic_summary_3000ce": "NVIDIA NIM Sentinel [Regional / Statutory Policy Friction] analyzed 'South Africa' from 1000 BCE baseline. Under the Fourth Seal: Pale Horse and March Gate, Botis (54.945 kHz) causes bottleneck friction across 10 predicted failure dates ending 2902-10-11. Applying Orbital Early-Warning Scanners via Amber & Chrysoberyl at 133.488 kHz shifts the node into the 90.0-100.0 kHz Ultra Green Patch, locking the 1.000 Unity Target."
      }
    },
    {
      "sandbox_id": "sentinel-c02",
      "status": "EXECUTED",
      "data": {
        "agent_index": 2,
        "chronos_phase": "Phase 1: Ancient Foundation Sweep (1000 BCE - 0 CE)",
        "diagnostic_scope": "Regional / Statutory Policy Friction",
        "target_node_subject": "South Africa",
        "biblical_apocalyptic_framework": {
          "apocalyptic_seal": "Fourth Seal: Pale Horse",
          "sealed_tribe": "Gad",
          "temporal_birth_gate": "March Gate",
          "church_anchor": "Pergamum",
          "base_degree_frequency_khz": "87.5 kHz",
          "zone_classification": "STABILIZED GREEN CORRIDOR"
        },
        "bottleneck": {
          "id": "B-18",
          "name": "Airport Customs Extortion in South Africa Context",
          "active_demon_driver": "Bathin",
          "frequency_khz": "58.275 kHz",
          "decay_velocity": 0.684,
          "destabilization_constant_floor": 0.666,
          "predictive_crash_schedule_10_dates_to_3000ce": [
            "2036-02-12",
            "2133-03-15",
            "2230-04-18",
            "2327-05-21",
            "2424-06-24",
            "2521-07-27",
            "2618-08-02",
            "2715-09-05",
            "2812-10-08",
            "2909-11-11"
          ]
        },
        "protocol": {
          "id": "P-18",
          "name": "Zero-Knowledge Biometric Lock Deployment",
          "ruling_shem_angel": "Caliel",
          "celestial_choir": "Thrones",
          "frequency_khz": "141.578 kHz",
          "current_restoration_speed": 0.732,
          "equilibrium_target": 1.0,
          "piezoelectric_gemstone_vector": "Aragonite & Scapolite"
        },
        "real_time_earth_vector": {
          "applied_speed": "0.6511x acceleration",
          "application_width_khz": "134.787 kHz bandwidth",
          "frequency_shift_to_ultra_green": "+36.725 kHz shift",
          "exact_spatial_target": "Airport Security Gates"
        },
        "prophetic_summary_3000ce": "NVIDIA NIM Sentinel [Regional / Statutory Policy Friction] analyzed 'South Africa' from 1000 BCE baseline. Under the Fourth Seal: Pale Horse and March Gate, Bathin (58.275 kHz) causes bottleneck friction across 10 predicted failure dates ending 2909-11-11. Applying Zero-Knowledge Biometric Lock via Aragonite & Scapolite at 141.578 kHz shifts the node into the 90.0-100.0 kHz Ultra Green Patch, locking the 1.000 Unity Target."
      }
    },
    {
      "sandbox_id": "sentinel-c03",
      "status": "EXECUTED",
      "data": {
        "agent_index": 3,
        "chronos_phase": "Phase 2: Historical Structural Arc (0 CE - 1800 CE)",
        "diagnostic_scope": "Regional / Statutory Policy Friction",
        "target_node_subject": "South Africa",
        "biblical_apocalyptic_framework": {
          "apocalyptic_seal": "Fourth Seal: Pale Horse",
          "sealed_tribe": "Asher",
          "temporal_birth_gate": "April Gate",
          "church_anchor": "Thyatira",
          "base_degree_frequency_khz": "92.5 kHz",
          "zone_classification": "STABILIZED GREEN CORRIDOR"
        },
        "bottleneck": {
          "id": "B-19",
          "name": "Industrial Labor Strikes in South Africa Context",
          "active_demon_driver": "Sallos",
          "frequency_khz": "61.605 kHz",
          "decay_velocity": 0.696,
          "destabilization_constant_floor": 0.666,
          "predictive_crash_schedule_10_dates_to_3000ce": [
            "2043-03-12",
            "2140-04-15",
            "2237-05-18",
            "2334-06-21",
            "2431-07-24",
            "2528-08-27",
            "2625-09-02",
            "2722-10-05",
            "2819-11-08",
            "2916-12-11"
          ]
        },
        "protocol": {
          "id": "P-19",
          "name": "Automated Profit-Share Ledger Deployment",
          "ruling_shem_angel": "Leuviah",
          "celestial_choir": "Thrones",
          "frequency_khz": "149.668 kHz",
          "current_restoration_speed": 0.754,
          "equilibrium_target": 1.0,
          "piezoelectric_gemstone_vector": "Moonstone & Selenite"
        },
        "real_time_earth_vector": {
          "applied_speed": "0.5977x acceleration",
          "application_width_khz": "142.489 kHz bandwidth",
          "frequency_shift_to_ultra_green": "+33.395 kHz shift",
          "exact_spatial_target": "Bargaining Council Arbitration"
        },
        "prophetic_summary_3000ce": "NVIDIA NIM Sentinel [Regional / Statutory Policy Friction] analyzed 'South Africa' from 1000 BCE baseline. Under the Fourth Seal: Pale Horse and April Gate, Sallos (61.605 kHz) causes bottleneck friction across 10 predicted failure dates ending 2916-12-11. Applying Automated Profit-Share Ledger via Moonstone & Selenite at 149.668 kHz shifts the node into the 90.0-100.0 kHz Ultra Green Patch, locking the 1.000 Unity Target."
      }
    },
    {
      "sandbox_id": "sentinel-c04",
      "status": "EXECUTED",
      "data": {
        "agent_index": 4,
        "chronos_phase": "Phase 2: Historical Structural Arc (0 CE - 1800 CE)",
        "diagnostic_scope": "Regional / Statutory Policy Friction",
        "target_node_subject": "South Africa",
        "biblical_apocalyptic_framework": {
          "apocalyptic_seal": "Fifth Seal: Altar of Martyrs",
          "sealed_tribe": "Asher",
          "temporal_birth_gate": "April Gate",
          "church_anchor": "Thyatira",
          "base_degree_frequency_khz": "97.5 kHz",
          "zone_classification": "STABILIZED GREEN CORRIDOR"
        },
        "bottleneck": {
          "id": "B-20",
          "name": "Fiat Currency Inflation Drag in South Africa Context",
          "active_demon_driver": "Purson",
          "frequency_khz": "64.935 kHz",
          "decay_velocity": 0.708,
          "destabilization_constant_floor": 0.666,
          "predictive_crash_schedule_10_dates_to_3000ce": [
            "2050-04-12",
            "2147-05-15",
            "2244-06-18",
            "2341-07-21",
            "2438-08-24",
            "2535-09-27",
            "2632-10-02",
            "2729-11-05",
            "2826-12-08",
            "2923-01-11"
          ]
        },
        "protocol": {
          "id": "P-20",
          "name": "Logos Asset-Backed Currency Deployment",
          "ruling_shem_angel": "Pahaliah",
          "celestial_choir": "Thrones",
          "frequency_khz": "157.758 kHz",
          "current_restoration_speed": 0.776,
          "equilibrium_target": 1.0,
          "piezoelectric_gemstone_vector": "Pearl & Mother of Pearl"
        },
        "real_time_earth_vector": {
          "applied_speed": "0.5442x acceleration",
          "application_width_khz": "150.191 kHz bandwidth",
          "frequency_shift_to_ultra_green": "+30.065 kHz shift",
          "exact_spatial_target": "Reserve Bank Vault Matrix"
        },
        "prophetic_summary_3000ce": "NVIDIA NIM Sentinel [Regional / Statutory Policy Friction] analyzed 'South Africa' from 1000 BCE baseline. Under the Fifth Seal: Altar of Martyrs and April Gate, Purson (64.935 kHz) causes bottleneck friction across 10 predicted failure dates ending 2923-01-11. Applying Logos Asset-Backed Currency via Pearl & Mother of Pearl at 157.758 kHz shifts the node into the 90.0-100.0 kHz Ultra Green Patch, locking the 1.000 Unity Target."
      }
    },
    {
      "sandbox_id": "sentinel-c05",
      "status": "EXECUTED",
      "data": {
        "agent_index": 5,
        "chronos_phase": "Phase 2: Historical Structural Arc (0 CE - 1800 CE)",
        "diagnostic_scope": "Regional / Statutory Policy Friction",
        "target_node_subject": "South Africa",
        "biblical_apocalyptic_framework": {
          "apocalyptic_seal": "Fifth Seal: Altar of Martyrs",
          "sealed_tribe": "Asher",
          "temporal_birth_gate": "April Gate",
          "church_anchor": "Thyatira",
          "base_degree_frequency_khz": "102.5 kHz",
          "zone_classification": "STABILIZED GREEN CORRIDOR"
        },
        "bottleneck": {
          "id": "B-21",
          "name": "Academic Knowledge Paywalls in South Africa Context",
          "active_demon_driver": "Morax",
          "frequency_khz": "68.265 kHz",
          "decay_velocity": 0.72,
          "destabilization_constant_floor": 0.666,
          "predictive_crash_schedule_10_dates_to_3000ce": [
            "2057-05-12",
            "2154-06-15",
            "2251-07-18",
            "2348-08-21",
            "2445-09-24",
            "2542-10-27",
            "2639-11-02",
            "2736-12-05",
            "2833-01-08",
            "2930-02-11"
          ]
        },
        "protocol": {
          "id": "P-21",
          "name": "Open Access Universal Vault Deployment",
          "ruling_shem_angel": "Nelchael",
          "celestial_choir": "Thrones",
          "frequency_khz": "165.848 kHz",
          "current_restoration_speed": 0.798,
          "equilibrium_target": 1.0,
          "piezoelectric_gemstone_vector": "White Chalcedony & Opal"
        },
        "real_time_earth_vector": {
          "applied_speed": "0.4908x acceleration",
          "application_width_khz": "157.893 kHz bandwidth",
          "frequency_shift_to_ultra_green": "+26.735 kHz shift",
          "exact_spatial_target": "University Supercomputing Grid"
        },
        "prophetic_summary_3000ce": "NVIDIA NIM Sentinel [Regional / Statutory Policy Friction] analyzed 'South Africa' from 1000 BCE baseline. Under the Fifth Seal: Altar of Martyrs and April Gate, Morax (68.265 kHz) causes bottleneck friction across 10 predicted failure dates ending 2930-02-11. Applying Open Access Universal Vault via White Chalcedony & Opal at 165.848 kHz shifts the node into the 90.0-100.0 kHz Ultra Green Patch, locking the 1.000 Unity Target."
      }
    },
    {
      "sandbox_id": "sentinel-c06",
      "status": "EXECUTED",
      "data": {
        "agent_index": 6,
        "chronos_phase": "Phase 3: Modern Jurisdictional Audit (1800 CE - Present)",
        "diagnostic_scope": "Global Consciousness & Macro Supply Drag",
        "target_node_subject": "South Africa",
        "biblical_apocalyptic_framework": {
          "apocalyptic_seal": "Fifth Seal: Altar of Martyrs",
          "sealed_tribe": "Asher",
          "temporal_birth_gate": "April Gate",
          "church_anchor": "Thyatira",
          "base_degree_frequency_khz": "107.5 kHz",
          "zone_classification": "STABILIZED GREEN CORRIDOR"
        },
        "bottleneck": {
          "id": "B-22",
          "name": "Air Freight Carbon Surcharges in South Africa Context",
          "active_demon_driver": "Ipos",
          "frequency_khz": "71.595 kHz",
          "decay_velocity": 0.732,
          "destabilization_constant_floor": 0.666,
          "predictive_crash_schedule_10_dates_to_3000ce": [
            "2064-06-12",
            "2161-07-15",
            "2258-08-18",
            "2355-09-21",
            "2452-10-24",
            "2549-11-27",
            "2646-12-02",
            "2743-01-05",
            "2840-02-08",
            "2937-03-11"
          ]
        },
        "protocol": {
          "id": "P-22",
          "name": "Hydrogen Airship Transit Mesh Deployment",
          "ruling_shem_angel": "Yeiayel",
          "celestial_choir": "Thrones",
          "frequency_khz": "173.939 kHz",
          "current_restoration_speed": 0.82,
          "equilibrium_target": 1.0,
          "piezoelectric_gemstone_vector": "Ulexite & Labradorite"
        },
        "real_time_earth_vector": {
          "applied_speed": "0.4373x acceleration",
          "application_width_khz": "165.596 kHz bandwidth",
          "frequency_shift_to_ultra_green": "+23.405 kHz shift",
          "exact_spatial_target": "Civil Aviation Radar Towers"
        },
        "prophetic_summary_3000ce": "NVIDIA NIM Sentinel [Global Consciousness & Macro Supply Drag] analyzed 'South Africa' from 1000 BCE baseline. Under the Fifth Seal: Altar of Martyrs and April Gate, Ipos (71.595 kHz) causes bottleneck friction across 10 predicted failure dates ending 2937-03-11. Applying Hydrogen Airship Transit Mesh via Ulexite & Labradorite at 173.939 kHz shifts the node into the 90.0-100.0 kHz Ultra Green Patch, locking the 1.000 Unity Target."
      }
    },
    {
      "sandbox_id": "sentinel-c07",
      "status": "EXECUTED",
      "data": {
        "agent_index": 7,
        "chronos_phase": "Phase 3: Modern Jurisdictional Audit (1800 CE - Present)",
        "diagnostic_scope": "Global Consciousness & Macro Supply Drag",
        "target_node_subject": "South Africa",
        "biblical_apocalyptic_framework": {
          "apocalyptic_seal": "Fifth Seal: Altar of Martyrs",
          "sealed_tribe": "Asher",
          "temporal_birth_gate": "April Gate",
          "church_anchor": "Thyatira",
          "base_degree_frequency_khz": "112.5 kHz",
          "zone_classification": "STABILIZED GREEN CORRIDOR"
        },
        "bottleneck": {
          "id": "B-23",
          "name": "Grid Fire Arson Propagation in South Africa Context",
          "active_demon_driver": "Aim",
          "frequency_khz": "74.925 kHz",
          "decay_velocity": 0.744,
          "destabilization_constant_floor": 0.666,
          "predictive_crash_schedule_10_dates_to_3000ce": [
            "2071-07-12",
            "2168-08-15",
            "2265-09-18",
            "2362-10-21",
            "2459-11-24",
            "2556-12-27",
            "2653-01-02",
            "2750-02-05",
            "2847-03-08",
            "2944-04-11"
          ]
        },
        "protocol": {
          "id": "P-23",
          "name": "Electro-Thermal Fire Arrays Deployment",
          "ruling_shem_angel": "Melahel",
          "celestial_choir": "Thrones",
          "frequency_khz": "182.029 kHz",
          "current_restoration_speed": 0.842,
          "equilibrium_target": 1.0,
          "piezoelectric_gemstone_vector": "Rhodonite & Pink Tourmaline"
        },
        "real_time_earth_vector": {
          "applied_speed": "0.3839x acceleration",
          "application_width_khz": "173.298 kHz bandwidth",
          "frequency_shift_to_ultra_green": "+20.075 kHz shift",
          "exact_spatial_target": "Municipal Fire & Rescue Grid"
        },
        "prophetic_summary_3000ce": "NVIDIA NIM Sentinel [Global Consciousness & Macro Supply Drag] analyzed 'South Africa' from 1000 BCE baseline. Under the Fifth Seal: Altar of Martyrs and April Gate, Aim (74.925 kHz) causes bottleneck friction across 10 predicted failure dates ending 2944-04-11. Applying Electro-Thermal Fire Arrays via Rhodonite & Pink Tourmaline at 182.029 kHz shifts the node into the 90.0-100.0 kHz Ultra Green Patch, locking the 1.000 Unity Target."
      }
    },
    {
      "sandbox_id": "sentinel-c08",
      "status": "EXECUTED",
      "data": {
        "agent_index": 8,
        "chronos_phase": "Phase 3: Modern Jurisdictional Audit (1800 CE - Present)",
        "diagnostic_scope": "Global Consciousness & Macro Supply Drag",
        "target_node_subject": "South Africa",
        "biblical_apocalyptic_framework": {
          "apocalyptic_seal": "Fifth Seal: Altar of Martyrs",
          "sealed_tribe": "Asher",
          "temporal_birth_gate": "April Gate",
          "church_anchor": "Thyatira",
          "base_degree_frequency_khz": "117.5 kHz",
          "zone_classification": "STABILIZED GREEN CORRIDOR"
        },
        "bottleneck": {
          "id": "B-24",
          "name": "Corporate Greenwashing Deception in South Africa Context",
          "active_demon_driver": "Naberius",
          "frequency_khz": "78.255 kHz",
          "decay_velocity": 0.756,
          "destabilization_constant_floor": 0.666,
          "predictive_crash_schedule_10_dates_to_3000ce": [
            "2078-08-12",
            "2175-09-15",
            "2272-10-18",
            "2369-11-21",
            "2466-12-24",
            "2563-01-27",
            "2660-02-02",
            "2757-03-05",
            "2854-04-08",
            "2951-05-11"
          ]
        },
        "protocol": {
          "id": "P-24",
          "name": "Pegasys Real-Time Audit Lock Deployment",
          "ruling_shem_angel": "Hahuiah",
          "celestial_choir": "Thrones",
          "frequency_khz": "190.119 kHz",
          "current_restoration_speed": 0.864,
          "equilibrium_target": 1.0,
          "piezoelectric_gemstone_vector": "Petalite & Morganite"
        },
        "real_time_earth_vector": {
          "applied_speed": "0.3304x acceleration",
          "application_width_khz": "181.0 kHz bandwidth",
          "frequency_shift_to_ultra_green": "+16.745 kHz shift",
          "exact_spatial_target": "Standards Authority Audit Servers"
        },
        "prophetic_summary_3000ce": "NVIDIA NIM Sentinel [Global Consciousness & Macro Supply Drag] analyzed 'South Africa' from 1000 BCE baseline. Under the Fifth Seal: Altar of Martyrs and April Gate, Naberius (78.255 kHz) causes bottleneck friction across 10 predicted failure dates ending 2951-05-11. Applying Pegasys Real-Time Audit Lock via Petalite & Morganite at 190.119 kHz shifts the node into the 90.0-100.0 kHz Ultra Green Patch, locking the 1.000 Unity Target."
      }
    },
    {
      "sandbox_id": "sentinel-c09",
      "status": "EXECUTED",
      "data": {
        "agent_index": 9,
        "chronos_phase": "Phase 4: Prophetic Horizon Calculation (2026 CE - 3000 CE)",
        "diagnostic_scope": "Global Consciousness & Macro Supply Drag",
        "target_node_subject": "South Africa",
        "biblical_apocalyptic_framework": {
          "apocalyptic_seal": "First Seal: White Horse",
          "sealed_tribe": "Judah",
          "temporal_birth_gate": "January Gate",
          "church_anchor": "Ephesus",
          "base_degree_frequency_khz": "2.5 kHz",
          "zone_classification": "SUB-HARMONIC RED ZONE (Entropy Drag)"
        },
        "bottleneck": {
          "id": "B-01",
          "name": "Fossil Fuel Monopolization in South Africa Context",
          "active_demon_driver": "Bael",
          "frequency_khz": "1.665 kHz",
          "decay_velocity": 0.768,
          "destabilization_constant_floor": 0.666,
          "predictive_crash_schedule_10_dates_to_3000ce": [
            "2085-09-12",
            "2182-10-15",
            "2279-11-18",
            "2376-12-21",
            "2473-01-24",
            "2570-02-27",
            "2667-03-02",
            "2764-04-05",
            "2861-05-08",
            "2958-06-11"
          ]
        },
        "protocol": {
          "id": "P-01",
          "name": "Decentralized Micro-Grid Nodes Deployment",
          "ruling_shem_angel": "Vehuiah",
          "celestial_choir": "Seraphim",
          "frequency_khz": "4.045 kHz",
          "current_restoration_speed": 0.886,
          "equilibrium_target": 1.0,
          "piezoelectric_gemstone_vector": "Red Jasper & Hematite"
        },
        "real_time_earth_vector": {
          "applied_speed": "0.277x acceleration",
          "application_width_khz": "3.851 kHz bandwidth",
          "frequency_shift_to_ultra_green": "+93.335 kHz shift",
          "exact_spatial_target": "Substation High-Voltage Busbars"
        },
        "prophetic_summary_3000ce": "NVIDIA NIM Sentinel [Global Consciousness & Macro Supply Drag] analyzed 'South Africa' from 1000 BCE baseline. Under the First Seal: White Horse and January Gate, Bael (1.665 kHz) causes bottleneck friction across 10 predicted failure dates ending 2958-06-11. Applying Decentralized Micro-Grid Nodes via Red Jasper & Hematite at 4.045 kHz shifts the node into the 90.0-100.0 kHz Ultra Green Patch, locking the 1.000 Unity Target."
      }
    },
    {
      "sandbox_id": "sentinel-c10",
      "status": "EXECUTED",
      "data": {
        "agent_index": 10,
        "chronos_phase": "Phase 4: Prophetic Horizon Calculation (2026 CE - 3000 CE)",
        "diagnostic_scope": "Global Consciousness & Macro Supply Drag",
        "target_node_subject": "South Africa",
        "biblical_apocalyptic_framework": {
          "apocalyptic_seal": "First Seal: White Horse",
          "sealed_tribe": "Judah",
          "temporal_birth_gate": "January Gate",
          "church_anchor": "Ephesus",
          "base_degree_frequency_khz": "7.5 kHz",
          "zone_classification": "SUB-HARMONIC RED ZONE (Entropy Drag)"
        },
        "bottleneck": {
          "id": "B-02",
          "name": "Border Trade Tariff Inertia in South Africa Context",
          "active_demon_driver": "Agares",
          "frequency_khz": "4.995 kHz",
          "decay_velocity": 0.78,
          "destabilization_constant_floor": 0.666,
          "predictive_crash_schedule_10_dates_to_3000ce": [
            "2092-10-12",
            "2189-11-15",
            "2286-12-18",
            "2383-01-21",
            "2480-02-24",
            "2577-03-27",
            "2674-04-02",
            "2771-05-05",
            "2868-06-08",
            "2965-07-11"
          ]
        },
        "protocol": {
          "id": "P-02",
          "name": "Maglev Automated Rail Mesh Deployment",
          "ruling_shem_angel": "Jeliel",
          "celestial_choir": "Seraphim",
          "frequency_khz": "12.135 kHz",
          "current_restoration_speed": 0.908,
          "equilibrium_target": 1.0,
          "piezoelectric_gemstone_vector": "Bloodstone & Garnet"
        },
        "real_time_earth_vector": {
          "applied_speed": "0.2235x acceleration",
          "application_width_khz": "11.553 kHz bandwidth",
          "frequency_shift_to_ultra_green": "+90.005 kHz shift",
          "exact_spatial_target": "Cross-Border Rail Junctions"
        },
        "prophetic_summary_3000ce": "NVIDIA NIM Sentinel [Global Consciousness & Macro Supply Drag] analyzed 'South Africa' from 1000 BCE baseline. Under the First Seal: White Horse and January Gate, Agares (4.995 kHz) causes bottleneck friction across 10 predicted failure dates ending 2965-07-11. Applying Maglev Automated Rail Mesh via Bloodstone & Garnet at 12.135 kHz shifts the node into the 90.0-100.0 kHz Ultra Green Patch, locking the 1.000 Unity Target."
      }
    }
  ]
}